.gitignore
LICENSE
MANIFEST.in
README.md
setup.py
crunchflow/__init__.py
crunchflow/util.py
crunchflow.egg-info/PKG-INFO
crunchflow.egg-info/SOURCES.txt
crunchflow.egg-info/dependency_links.txt
crunchflow.egg-info/not-zip-safe
crunchflow.egg-info/requires.txt
crunchflow.egg-info/top_level.txt
crunchflow/output/__init__.py
crunchflow/output/tec.py
crunchflow/output/timeseries.py
docs/Makefile
docs/conf.py
docs/index.rst
docs/make.bat
docs/requirements.txt