Metadata-Version: 2.1
Name: crunchflow
Version: 1.0.4
Summary: Python toolbox for working with the CrunchFlow reactive transport model
Home-page: https://github.com/zperzan/python-crunchflow
Author: Zach Perzan
Author-email: zperzan@stanford.edu
License: GPL
Platform: UNKNOWN
Classifier: Programming Language :: Python :: 3
Classifier: License :: OSI Approved :: GNU General Public License (GPL)
Requires-Python: >=3.6
